CoursesHack4u/__init__.py
CoursesHack4u/courses.py
CoursesHack4u/utils.py
CoursesHack4u-0.2024.2025.dist-info/METADATA
CoursesHack4u-0.2024.2025.dist-info/WHEEL
CoursesHack4u-0.2024.2025.dist-info/top_level.txt
CoursesHack4u-0.2024.2025.dist-info/RECORD
