Metadata-Version: 2.1
Name: CoursesHack4u
Version: 0.2024.2025
Home-page: https://hack4u.io
Author: Luis Ovejero
